Metadata-Version: 2.1
Name: octoparse-python
Version: 0.1.1
Summary: API wrapper for Octoparse written in Python
Home-page: https://github.com/GearPlug/octoparse-python
Author: Miguel Ferrer
Author-email: ingferrermiguel@gmail.com
License: MIT
Platform: UNKNOWN
